crosscheck/__init__.py
crosscheck-0.0.0.2.dist-info/METADATA
crosscheck-0.0.0.2.dist-info/WHEEL
crosscheck-0.0.0.2.dist-info/RECORD
