Metadata-Version: 2.1
Name: crosscheck
Version: 0.0.0.2
Summary: 
Home-page: https://github.com/APN-Pucky/crosscheck
Author: Alexander Puck Neuwirth
Author-email: alexander@neuwirth-informatik.de
Requires-Python: >=3.8,<4.0
Classifier: Programming Language :: Python :: 3
Classifier: Programming Language :: Python :: 3.8
Classifier: Programming Language :: Python :: 3.9
Classifier: Programming Language :: Python :: 3.10
Classifier: Programming Language :: Python :: 3.11
Requires-Dist: matplotlib
Requires-Dist: numpy
Requires-Dist: pandas (>=1.0.0)
Requires-Dist: scipy (>=1.7.0)
Requires-Dist: sympy
Requires-Dist: tqdm
Project-URL: Repository, https://github.com/APN-Pucky/crosscheck
